claude_board/__init__.py
claude_board/_version.py
claude_board/cli.py
claude_board/config.py
claude_board/models.py
claude_board/py.typed
claude_board/server.py
claude_board/state.py
claude_board/types.py
claude_board/ble/__init__.py
claude_board/chat/__init__.py
claude_board/chat/session.py
claude_board/chat/terminal_client.py
claude_board/hooks/__init__.py
claude_board/hooks/permission_hook.py
claude_board/hooks/session_end_hook.py
claude_board/hooks/session_start_hook.py
claude_board/hooks/stop_hook.py
claude_board/hooks/todo_hook.py
claude_board/web/app.js
claude_board/web/index.html
claude_board/web/style.css
claude_board-0.3.13.dist-info/METADATA
claude_board-0.3.13.dist-info/WHEEL
claude_board-0.3.13.dist-info/entry_points.txt
claude_board-0.3.13.dist-info/licenses/LICENSE
claude_board-0.3.13.dist-info/RECORD
