Metadata-Version: 2.4
Name: claude-board
Version: 0.3.13
Summary: Physical console for Claude Code - approve/deny permissions from your phone or hardware device
Project-URL: Homepage, https://github.com/pescn/claude-board
Project-URL: Documentation, https://github.com/pescn/claude-board#readme
Project-URL: Repository, https://github.com/pescn/claude-board
Project-URL: Issues, https://github.com/pescn/claude-board/issues
Author: pescn
License: AGPL-3.0-or-later
License-File: LICENSE
Keywords: approval,claude,claude-code,console,permissions
Classifier: Development Status :: 3 - Alpha
Classifier: Environment :: Console
Classifier: Environment :: Web Environment
Classifier: Framework :: FastAPI
Classifier: Intended Audience :: Developers
Classifier: License :: OSI Approved :: GNU Affero General Public License v3 or later (AGPLv3+)
Classifier: Operating System :: OS Independent
Classifier: Programming Language :: Python :: 3
Classifier: Programming Language :: Python :: 3.10
Classifier: Programming Language :: Python :: 3.11
Classifier: Programming Language :: Python :: 3.12
Classifier: Topic :: Software Development :: Build Tools
Classifier: Topic :: Utilities
Requires-Python: >=3.10
Requires-Dist: fastapi>=0.109.0
Requires-Dist: pyte>=0.8.2
Requires-Dist: qrcode>=8.2
Requires-Dist: rich>=13.0.0
Requires-Dist: typer>=0.9.0
Requires-Dist: uvicorn[standard]>=0.27.0
Provides-Extra: ble
Requires-Dist: bleak>=0.21.0; extra == 'ble'
Provides-Extra: dev
Requires-Dist: httpx>=0.25.0; extra == 'dev'
Requires-Dist: pytest-asyncio>=0.21.0; extra == 'dev'
Requires-Dist: pytest>=7.0.0; extra == 'dev'
